Metadata-Version: 2.1
Name: image_processing-package-gleyson-atanazio
Version: 0.0.4
Summary: Módulo para processamento e comparação de imagens.
Home-page: https://github.com/atnzpe/processar-imagem-py
Author: Gleyson Atanazio
Author-email: gleysonasilva@gmail.com
Requires-Python: >=3.8
Requires-Dist: asttokens
Requires-Dist: attrs
Requires-Dist: backcall
Requires-Dist: beautifulsoup4
Requires-Dist: bleach
Requires-Dist: certifi
Requires-Dist: charset-normalizer
Requires-Dist: colorama
Requires-Dist: contourpy
Requires-Dist: cycler
Requires-Dist: decorator
Requires-Dist: defusedxml
Requires-Dist: docopt
Requires-Dist: docutils
Requires-Dist: executing
Requires-Dist: fastjsonschema
Requires-Dist: fonttools
Requires-Dist: idna
Requires-Dist: imageio
Requires-Dist: importlib-metadata
Requires-Dist: ipython
Requires-Dist: jaraco.classes
Requires-Dist: jaraco.context
Requires-Dist: jaraco.functools
Requires-Dist: jedi
Requires-Dist: Jinja2
Requires-Dist: jsonschema
Requires-Dist: jsonschema-specifications
Requires-Dist: jupyter-client
Requires-Dist: jupyter-core
Requires-Dist: jupyterlab-pygments
Requires-Dist: keyring
Requires-Dist: kiwisolver
Requires-Dist: lazy-loader
Requires-Dist: markdown-it-py
Requires-Dist: MarkupSafe
Requires-Dist: matplotlib
Requires-Dist: matplotlib-inline
Requires-Dist: mdurl
Requires-Dist: mistune
Requires-Dist: more-itertools
Requires-Dist: nbclient
Requires-Dist: nbconvert
Requires-Dist: nbformat
Requires-Dist: networkx
Requires-Dist: nh3
Requires-Dist: numpy
Requires-Dist: packaging
Requires-Dist: pandocfilters
Requires-Dist: parso
Requires-Dist: pickleshare
Requires-Dist: pillow
Requires-Dist: pipreqs
Requires-Dist: pkginfo
Requires-Dist: platformdirs
Requires-Dist: prompt-toolkit
Requires-Dist: pure-eval
Requires-Dist: Pygments
Requires-Dist: pyparsing
Requires-Dist: python-dateutil
Requires-Dist: pywin32
Requires-Dist: pywin32-ctypes
Requires-Dist: pyzmq
Requires-Dist: readme-renderer
Requires-Dist: referencing
Requires-Dist: requests
Requires-Dist: requests-toolbelt
Requires-Dist: rfc3986
Requires-Dist: rich
Requires-Dist: rpds-py
Requires-Dist: scikit-image
Requires-Dist: scipy
Requires-Dist: setuptools
Requires-Dist: six
Requires-Dist: soupsieve
Requires-Dist: stack-data
Requires-Dist: tifffile
Requires-Dist: tinycss2
Requires-Dist: tornado
Requires-Dist: traitlets
Requires-Dist: twine
Requires-Dist: urllib3
Requires-Dist: wcwidth
Requires-Dist: webencodings
Requires-Dist: yarg
Requires-Dist: zipp
